locking/__init__.py
locking/baselock.py
locking/config.py
locking/custom_exceptions.py
locking/heartbeater.py
locking/utils.py
locking/dynamolock/__init__.py
locking/dynamolock/dynamolock.py
locking/filelock/__init__.py
locking/filelock/filelock.py
locking/redislock/__init__.py
locking/redislock/redislock.py
locking/socketlock/__init__.py
locking/socketlock/socketlock.py
locking-1.1.6.dist-info/METADATA
locking-1.1.6.dist-info/WHEEL
locking-1.1.6.dist-info/top_level.txt
locking-1.1.6.dist-info/RECORD
