Metadata-Version: 2.1
Name: locking
Version: 1.1.6
Summary: Provide locks with interface similar to those from threading  and multiprocessing, which are applicable in other situations.
Home-page: https://github.com/jbylund/locking
Author: Joseph Bylund
Author-email: joseph.bylund@gmail.com
Maintainer: Joseph Bylund
Maintainer-email: joseph.bylund@gmail.com
License: UNKNOWN
Platform: UNKNOWN
